hydroclassification/__init__.py
hydroclassification/test.py
package/__init__.py
package/test.py
hydroclassification-0.5.dist-info/LICENSE
hydroclassification-0.5.dist-info/METADATA
hydroclassification-0.5.dist-info/WHEEL
hydroclassification-0.5.dist-info/top_level.txt
hydroclassification-0.5.dist-info/RECORD
