Metadata-Version: 2.1
Name: hydroclassification
Version: 0.5
Summary: Package for hydrogeological classifcation
Author: Brayan A. Quiceno
License-File: LICENSE
Requires-Dist: numpy
Requires-Dist: pandas
